{
  "type": "Feature",
  "properties": {
    "gn:admin1_code":"00",
    "gn:asciiname":"Port Louis Settlement",
    "gn:country_code":"FK",
    "gn:dem":20,
    "gn:feature_class":"P",
    "gn:feature_code":"PPL",
    "gn:name":"Port Louis Settlement",
    "gn:population":0,
    "gn:timezone":"Atlantic/Stanley",
    "iso:country":"FK",
    "name:und_x_variant":[
        "Anson",
        "Saint Louis",
        "Soledad",
        "Port Louis",
        "Port Louis Settlement"
    ],
    "wof:name":"Port Louis Settlement",
    "wof:placetype":"locality"
},
  "geometry": {"coordinates":[-58.10896,-51.52367],"type":"Point"}
}