{
  "type": "Feature",
  "properties": {
    "gn:admin1_code":"00",
    "gn:asciiname":"Saunders Island Settlement",
    "gn:country_code":"FK",
    "gn:dem":15,
    "gn:feature_class":"P",
    "gn:feature_code":"PPL",
    "gn:name":"Saunders Island Settlement",
    "gn:population":0,
    "gn:timezone":"Atlantic/Stanley",
    "iso:country":"FK",
    "wof:name":"Saunders Island Settlement",
    "wof:placetype":"locality"
},
  "geometry": {"coordinates":[-60.08726,-51.36589],"type":"Point"}
}