{
  "type": "Feature",
  "properties": {
    "gn:admin1_code":"00",
    "gn:asciiname":"Horseshoe Bay",
    "gn:country_code":"FK",
    "gn:dem":3,
    "gn:feature_class":"P",
    "gn:feature_code":"PPL",
    "gn:name":"Horseshoe Bay",
    "gn:population":0,
    "gn:timezone":"Atlantic/Stanley",
    "iso:country":"FK",
    "name:ceb_x_preferred":[
        "Horseshoe Bay"
    ],
    "name:deu_x_preferred":[
        "Horseshoe Bay"
    ],
    "name:fra_x_preferred":[
        "Horseshoe Bay"
    ],
    "name:jpn_x_preferred":[
        "\u30db\u30fc\u30b9\u30b7\u30e5\u30fc\u30fb\u30d9\u30a4"
    ],
    "name:swe_x_preferred":[
        "Horseshoe Bay"
    ],
    "wof:name":"Horseshoe Bay",
    "wof:placetype":"locality"
},
  "geometry": {"coordinates":[-58.21666999999999,-51.53333],"type":"Point"}
}