{
  "type": "Feature",
  "properties": {
    "gn:admin1_code":"00",
    "gn:asciiname":"Green Patch Settlement",
    "gn:country_code":"FK",
    "gn:dem":-9999,
    "gn:feature_class":"P",
    "gn:feature_code":"PPL",
    "gn:name":"Green Patch Settlement",
    "gn:population":0,
    "gn:timezone":"Atlantic/Stanley",
    "iso:country":"FK",
    "wof:name":"Green Patch Settlement",
    "wof:placetype":"locality"
},
  "geometry": {"coordinates":[-58.11785,-51.54833],"type":"Point"}
}