{
  "type": "Feature",
  "properties": {
    "gn:admin1_code":"00",
    "gn:asciiname":"Camp Verde",
    "gn:cc2":"FK",
    "gn:country_code":"FK",
    "gn:dem":32,
    "gn:feature_class":"P",
    "gn:feature_code":"PPL",
    "gn:name":"Camp Verde",
    "gn:population":0,
    "gn:timezone":"Atlantic/Stanley",
    "iso:country":"FK",
    "name:und_x_variant":[
        "Campo Verde",
        "Camp Verde"
    ],
    "wof:name":"Camp Verde",
    "wof:placetype":"locality"
},
  "geometry": {"coordinates":[-58.96666999999999,-51.53333],"type":"Point"}
}