{
  "type": "Feature",
  "properties": {
    "gn:admin1_code":"00",
    "gn:asciiname":"Westpoint Island Settlement",
    "gn:country_code":"FK",
    "gn:dem":26,
    "gn:feature_class":"P",
    "gn:feature_code":"PPL",
    "gn:name":"Westpoint Island Settlement",
    "gn:population":0,
    "gn:timezone":"Atlantic/Stanley",
    "iso:country":"FK",
    "wof:name":"Westpoint Island Settlement",
    "wof:placetype":"locality"
},
  "geometry": {"coordinates":[-60.68685,-51.34879],"type":"Point"}
}