{
  "type": "Feature",
  "properties": {
    "gn:admin1_code":"00",
    "gn:asciiname":"Dunnose Head Settlement",
    "gn:country_code":"FK",
    "gn:dem":41,
    "gn:feature_class":"P",
    "gn:feature_code":"PPL",
    "gn:name":"Dunnose Head Settlement",
    "gn:population":0,
    "gn:timezone":"Atlantic/Stanley",
    "iso:country":"FK",
    "name:und_x_variant":[
        "Dunnose Head",
        "Dunnose Head Settlement"
    ],
    "wof:name":"Dunnose Head Settlement",
    "wof:placetype":"locality"
},
  "geometry": {"coordinates":[-60.41656999999999,-51.74147],"type":"Point"}
}